lichvansu/__init__.py
lichvansu/lvs.py
lichvansu-2021.8.9.dist-info/LICENSE
lichvansu-2021.8.9.dist-info/METADATA
lichvansu-2021.8.9.dist-info/WHEEL
lichvansu-2021.8.9.dist-info/top_level.txt
lichvansu-2021.8.9.dist-info/RECORD
