Metadata-Version: 2.1
Name: lichvansu
Version: 2021.8.9
Summary: https://vnhass.blogspot.com/
Home-page: https://github.com/pypa/sampleproject
Author: @trumxuquang
Author-email: trumxuquang@gmail.com
License: UNKNOWN
Platform: UNKNOWN
Classifier: Programming Language :: Python :: 3
Classifier: Programming Language :: Python :: 3.6
Classifier: Programming Language :: Python :: 3.7
Classifier: Programming Language :: Python :: 3.8
Classifier: Programming Language :: Python :: 3.9
Classifier: Programming Language :: Python :: 3 :: Only
License-File: LICENSE
Requires-Dist: requests (<3,>=2.25)
